jupyterlab_webrtc_docprovider/__init__.py
jupyterlab_webrtc_docprovider/_version.py
jupyterlab_webrtc_docprovider/labextension/package.json
jupyterlab_webrtc_docprovider/labextension/schemas/@jupyterlite/webrtc-docprovider/package.json.orig
jupyterlab_webrtc_docprovider/labextension/schemas/@jupyterlite/webrtc-docprovider/plugin.json
jupyterlab_webrtc_docprovider/labextension/static/494.b4474f380b4cef5cfd00.js
jupyterlab_webrtc_docprovider/labextension/static/494.b4474f380b4cef5cfd00.js.LICENSE.txt
jupyterlab_webrtc_docprovider/labextension/static/494.b4474f380b4cef5cfd00.js.map
jupyterlab_webrtc_docprovider/labextension/static/568.f675be4441bc032f8b37.js
jupyterlab_webrtc_docprovider/labextension/static/568.f675be4441bc032f8b37.js.map
jupyterlab_webrtc_docprovider/labextension/static/57.759085219a7619f2ecdb.js
jupyterlab_webrtc_docprovider/labextension/static/57.759085219a7619f2ecdb.js.map
jupyterlab_webrtc_docprovider/labextension/static/676.91dd2945fefd085c521d.js
jupyterlab_webrtc_docprovider/labextension/static/676.91dd2945fefd085c521d.js.map
jupyterlab_webrtc_docprovider/labextension/static/700.742b092f123028dfb417.js
jupyterlab_webrtc_docprovider/labextension/static/700.742b092f123028dfb417.js.map
jupyterlab_webrtc_docprovider/labextension/static/705.1a740902d86325bfa914.js
jupyterlab_webrtc_docprovider/labextension/static/705.1a740902d86325bfa914.js.map
jupyterlab_webrtc_docprovider/labextension/static/747.740c42137a1b1e362974.js
jupyterlab_webrtc_docprovider/labextension/static/747.740c42137a1b1e362974.js.map
jupyterlab_webrtc_docprovider/labextension/static/757.7bc7dfb78c910061e227.js
jupyterlab_webrtc_docprovider/labextension/static/757.7bc7dfb78c910061e227.js.map
jupyterlab_webrtc_docprovider/labextension/static/remoteEntry.8dcc730aedc487734a23.js
jupyterlab_webrtc_docprovider/labextension/static/remoteEntry.8dcc730aedc487734a23.js.map
jupyterlab_webrtc_docprovider/labextension/static/style.js
jupyterlab_webrtc_docprovider-0.1.1.dist-info/LICENSE
jupyterlab_webrtc_docprovider-0.1.1.dist-info/METADATA
jupyterlab_webrtc_docprovider-0.1.1.dist-info/WHEEL
jupyterlab_webrtc_docprovider-0.1.1.dist-info/top_level.txt
jupyterlab_webrtc_docprovider-0.1.1.dist-info/RECORD
